localhost_run/__init__.py
localhost_run/asetukset.py
localhost_run/konteksti.py
localhost_run/management/__init__.py
localhost_run/management/commands/__init__.py
localhost_run/management/commands/runserver.py
django_localhost_run-0.1.dist-info/METADATA
django_localhost_run-0.1.dist-info/WHEEL
django_localhost_run-0.1.dist-info/entry_points.txt
django_localhost_run-0.1.dist-info/historia.json
django_localhost_run-0.1.dist-info/top_level.txt
django_localhost_run-0.1.dist-info/RECORD
