Metadata-Version: 2.1
Name: django-localhost-run
Version: 0.1
Summary: Localhost.run-integraatio django-kehityspalvelimessa
Author-email: Antti Hautaniemi <antti.hautaniemi@me.com>
License: Tekijänoikeus 2020– Antti Hautaniemi
Project-URL: Repository, https://github.com/an7oine/django-pistoke.git
Requires-Python: >=3.8
Requires-Dist: django>=4.2
